{"files":{"unAventonApp_modules_Git_py":{"index":{"nums":[1,28,3,15,0,0,0],"html_filename":"unAventonApp_modules_Git_py.html","relative_filename":"unAventonApp/modules/Git.py"},"hash":"0e3baafbfdceacd269eef9dd8379c99b"},"unAventonApp_views_py":{"index":{"nums":[1,46,6,35,0,0,0],"html_filename":"unAventonApp_views_py.html","relative_filename":"unAventonApp/views.py"},"hash":"6764b1bae639de3025c480fe21f5ef22"},"unAventonApp_models_py":{"index":{"nums":[1,284,11,94,0,0,0],"html_filename":"unAventonApp_models_py.html","relative_filename":"unAventonApp/models.py"},"hash":"51cd062343602fb6b1a8b77187227952"},"unAventonApp_ajax_py":{"index":{"nums":[1,72,8,65,0,0,0],"html_filename":"unAventonApp_ajax_py.html","relative_filename":"unAventonApp/ajax.py"},"hash":"d3bb58800dbcbc7b6a6f33e021b7eef1"},"unAventonApp_templatetags_unAventonApp_extras_py":{"index":{"nums":[1,8,4,4,0,0,0],"html_filename":"unAventonApp_templatetags_unAventonApp_extras_py.html","relative_filename":"unAventonApp/templatetags/unAventonApp_extras.py"},"hash":"6c5be55c32324693da258fc32de46c71"}},"settings":"e8db4b1b3dd209e007cc0e6d8a997cf3","version":"4.5.1","format":1}